hocr_tools_lib/__init__.py
hocr_tools_lib/py.typed
hocr_tools_lib/tools/__init__.py
hocr_tools_lib/tools/hocr_check.py
hocr_tools_lib/tools/hocr_combine.py
hocr_tools_lib/tools/hocr_cut.py
hocr_tools_lib/tools/hocr_eval.py
hocr_tools_lib/tools/hocr_eval_geom.py
hocr_tools_lib/tools/hocr_eval_lines.py
hocr_tools_lib/tools/hocr_extract_images.py
hocr_tools_lib/tools/hocr_lines.py
hocr_tools_lib/tools/hocr_merge_dc.py
hocr_tools_lib/tools/hocr_pdf.py
hocr_tools_lib/tools/hocr_split.py
hocr_tools_lib/tools/hocr_wordfreq.py
hocr_tools_lib/utils/__init__.py
hocr_tools_lib/utils/edit_utils.py
hocr_tools_lib/utils/node_utils.py
hocr_tools_lib/utils/rectangle_utils.py
hocr_tools_lib/utils/text_utils.py
hocr_tools_lib/utils/typing_utils.py
hocr_tools_lib-1.2.0.dist-info/licenses/LICENSE
hocr_tools_lib-1.2.0.dist-info/METADATA
hocr_tools_lib-1.2.0.dist-info/WHEEL
hocr_tools_lib-1.2.0.dist-info/entry_points.txt
hocr_tools_lib-1.2.0.dist-info/top_level.txt
hocr_tools_lib-1.2.0.dist-info/RECORD
