Metadata-Version: 2.4
Name: hocr-tools-lib
Version: 1.2.0
Summary: Advanced tools for hOCR integration (library version)
Author: Thomas Breuel, stefan6419846 (library version)
License-Expression: Apache-2.0
Project-URL: Homepage, https://github.com/stefan6419846/hocr-tools
Project-URL: Documentation, https://hocr-tools-lib.readthedocs.io
Project-URL: Repository, https://github.com/stefan6419846/hocr-tools
Project-URL: Issues, https://github.com/stefan6419846/hocr-tools/issues
Project-URL: Changelog, https://github.com/stefan6419846/hocr-tools/blob/next/CHANGELOG.md
Keywords: ocr,hocr,xhtml
Classifier: Development Status :: 5 - Production/Stable
Classifier: Environment :: Console
Classifier: Intended Audience :: End Users/Desktop
Classifier: Operating System :: OS Independent
Classifier: Programming Language :: Python :: 3 :: Only
Classifier: Topic :: Multimedia :: Graphics :: Graphics Conversion
Classifier: Topic :: Scientific/Engineering :: Image Recognition
Classifier: Topic :: Utilities
Classifier: Typing :: Typed
Requires-Python: <4,>=3.9
License-File: LICENSE
Requires-Dist: Pillow>=9.3.0
Requires-Dist: lxml>=3.5.0
Requires-Dist: reportlab>=3.3.0
Requires-Dist: python-bidi
Provides-Extra: dev
Requires-Dist: beautifulsoup4; extra == "dev"
Requires-Dist: requests; extra == "dev"
Requires-Dist: pypdf; extra == "dev"
Requires-Dist: importlib-resources; python_version < "3.10" and extra == "dev"
Requires-Dist: flake8; extra == "dev"
Requires-Dist: flake8-bugbear; extra == "dev"
Requires-Dist: pep8-naming; extra == "dev"
Requires-Dist: mypy; extra == "dev"
Requires-Dist: types-beautifulsoup4; extra == "dev"
Requires-Dist: types-html5lib; extra == "dev"
Requires-Dist: types-lxml; extra == "dev"
Requires-Dist: types-Pillow; extra == "dev"
Requires-Dist: types-requests; extra == "dev"
Requires-Dist: codespell; extra == "dev"
Provides-Extra: docs
Requires-Dist: sphinx; extra == "docs"
Requires-Dist: furo; extra == "docs"
Dynamic: license-file
